[
  { "type": "title", "lang": "ja", "translation": "rripvk3v", "identifier": "" },
  { "type": "topic", "lang": "", "translation": "jnfvwgrt", "identifier": "" },
  {
    "type": "entity_lists",
    "items": [
      {
        "type": "entity_list",
        "lang": "",
        "translation": "ffhq0gea",
        "items": [
          { "active": "1", "code": "azdq", "identifier": "", "image": "", "lang": "", "route": "8tc5zxs0", "translation": ["twb054en"], "type": "route3" },
          { "active": "1", "code": "azdq_1", "identifier": "", "image": "", "lang": "", "route": "rgsezyvk", "translation": ["ao3emrlo"], "type": "route3" },
          { "active": "1", "code": "azdq_1", "identifier": "", "image": "", "lang": "", "route": "yvc5yyzi", "translation": ["bq7o4wqr"], "type": "route3" },
          { "active": "1", "code": "azdq_1", "identifier": "", "image": "", "lang": "", "route": "lno4a9jy", "translation": ["8tm3rfdc"], "type": "route3" },
          { "active": "1", "code": "azdq", "identifier": "", "image": "", "lang": "", "route": "giffr8vy", "translation": ["v01gsiwo"], "type": "route3" },
          { "active": "1", "code": "azdq", "identifier": "", "image": "", "lang": "", "route": "43r7u0b3", "translation": ["kohck17v"], "type": "route3" },
          { "active": "1", "code": "azdq_1", "identifier": "", "image": "", "lang": "", "route": "n9uohpm3", "translation": ["blc3yx23"], "type": "route3" },
          { "active": "1", "code": "azdq_1", "identifier": "", "image": "", "lang": "", "route": "73agm7xe", "translation": ["lrbiiogb"], "type": "route3" },
          { "active": "1", "code": "azdq", "identifier": "", "image": "", "lang": "", "route": "mo84rsgp", "translation": ["iiopso5q"], "type": "route3" },
          { "active": "1", "code": "azdq", "identifier": "", "image": "", "lang": "", "route": "qsby8vrz", "translation": ["bh247381"], "type": "route3" },
          { "active": "1", "code": "azdq", "identifier": "", "image": "", "lang": "", "route": "vorhih72", "translation": ["z8jewlpk"], "type": "route3" },
          { "active": "1", "code": "azdq_1", "identifier": "", "image": "", "lang": "", "route": "4le1zg1p", "translation": ["kwo8ouac"], "type": "route3" },
          { "active": "1", "code": "azdq_1", "identifier": "", "image": "", "lang": "", "route": "v915wy8k", "translation": ["4bwdhhmz"], "type": "route3" },
          { "active": "1", "code": "azdq_1", "identifier": "", "image": "", "lang": "", "route": "bbt9rdzs", "translation": ["l13uczum"], "type": "route3" },
          { "active": "1", "code": "azdq", "identifier": "", "image": "", "lang": "", "route": "rzhxkwg4", "translation": ["wyxchkgo"], "type": "route3" },
          { "active": "1", "code": "azdq", "identifier": "", "image": "", "lang": "", "route": "fznalc0t", "translation": ["o273du9k"], "type": "route3" },
          { "active": "1", "code": "azdq", "identifier": "", "image": "", "lang": "", "route": "js3thp2i", "translation": ["yz04hagr"], "type": "route3" },
          { "active": "1", "code": "azdq_1", "identifier": "", "image": "", "lang": "", "route": "uw9zn1pf", "translation": ["zemh3n34"], "type": "route3" },
          { "active": "1", "code": "azdq_1", "identifier": "", "image": "", "lang": "", "route": "1az9758s", "translation": ["ish3as9t"], "type": "route3" },
          { "active": "1", "code": "azdq_1", "identifier": "", "image": "", "lang": "", "route": "coafyqkn", "translation": ["k3ldy7oc"], "type": "route3" },
          { "active": "1", "code": "azdq", "identifier": "", "image": "", "lang": "", "route": "ti1c9xd1", "translation": ["evvk9x5s"], "type": "route3" },
          { "active": "1", "code": "azdq_1", "identifier": "", "image": "", "lang": "", "route": "dtin11bo", "translation": ["hcawgp3e"], "type": "route3" },
          { "active": "1", "code": "azdq", "identifier": "", "image": "", "lang": "", "route": "at80agmf", "translation": ["w2v3vdqj"], "type": "route3" },
          { "active": "1", "code": "azdq_1", "identifier": "", "image": "", "lang": "", "route": "22t5savy", "translation": ["jashw8c4"], "type": "route3" },
          { "active": "1", "code": "azdq", "identifier": "", "image": "", "lang": "", "route": "b1t423l5", "translation": ["o5h8jrz7"], "type": "route3" },
          { "active": "1", "code": "azdq", "identifier": "", "image": "", "lang": "", "route": "xa7w0mka", "translation": ["7gpacv8a"], "type": "route3" },
          { "active": "1", "code": "azdq", "identifier": "", "image": "", "lang": "", "route": "rpmtytnx", "translation": ["8y3r7f95"], "type": "route3" },
          { "active": "1", "code": "azdq", "identifier": "", "image": "", "lang": "", "route": "78fh1lat", "translation": ["s48pkn9o"], "type": "route3" },
          { "active": "1", "code": "azdq_1", "identifier": "", "image": "", "lang": "", "route": "l27o5lmr", "translation": ["y88pcryx"], "type": "route3" },
          { "active": "1", "code": "azdq_1", "identifier": "", "image": "", "lang": "", "route": "vbxni5re", "translation": ["q3ibadex"], "type": "route3" }
        ]
      },
      {
        "type": "entity_list",
        "lang": "",
        "translation": "j4un27gi",
        "items": [
          { "active": "1", "code": "azdq_1", "identifier": "", "image": "", "lang": "", "route": "x1lplxft", "translation": ["8tm3rfdc"], "type": "route3" },
          { "active": "1", "code": "azdq_1", "identifier": "", "image": "", "lang": "", "route": "4kevb7m0", "translation": ["v01gsiwo"], "type": "route3" },
          { "active": "1", "code": "azdq_1", "identifier": "", "image": "", "lang": "", "route": "lxbohw9o", "translation": ["blc3yx23"], "type": "route3" },
          { "active": "1", "code": "azdq_1", "identifier": "", "image": "", "lang": "", "route": "wnanwtlb", "translation": ["iiopso5q"], "type": "route3" },
          { "active": "1", "code": "azdq_1", "identifier": "", "image": "", "lang": "", "route": "v1k2nwp7", "translation": ["vps8psh1"], "type": "route3" },
          { "active": "1", "code": "azdq_1", "identifier": "", "image": "", "lang": "", "route": "y0tsz8jy", "translation": ["l13uczum"], "type": "route3" },
          { "active": "1", "code": "azdq_1", "identifier": "", "image": "", "lang": "", "route": "2tmy15w5", "translation": ["ish3as9t"], "type": "route3" },
          { "active": "1", "code": "azdq_1", "identifier": "", "image": "", "lang": "", "route": "qoby5qxv", "translation": ["4konpxjf"], "type": "route3" },
          { "active": "1", "code": "azdq_1", "identifier": "", "image": "", "lang": "", "route": "gmqipaie", "translation": ["hjotfcxg"], "type": "route3" },
          { "active": "1", "code": "azdq_1", "identifier": "", "image": "", "lang": "", "route": "qp7mptn3", "translation": ["l79zyvhq"], "type": "route3" },
          { "active": "1", "code": "azdq_1", "identifier": "", "image": "", "lang": "", "route": "jka4mqv8", "translation": ["jashw8c4"], "type": "route3" },
          { "active": "1", "code": "azdq_1", "identifier": "", "image": "", "lang": "", "route": "8locbuu8", "translation": ["o5h8jrz7"], "type": "route3" },
          { "active": "1", "code": "azdq_1", "identifier": "", "image": "", "lang": "", "route": "vvpa2gi7", "translation": ["q3ibadex"], "type": "route3" },
          { "active": "1", "code": "azdq_1", "identifier": "", "image": "", "lang": "", "route": "gcbgwjcb", "translation": ["mw2dznxy"], "type": "route3" },
          { "active": "1", "code": "azdq", "identifier": "", "image": "", "lang": "", "route": "yzn4plnd", "translation": ["1npst8z9"], "type": "route3" },
          { "active": "1", "code": "azdq", "identifier": "", "image": "", "lang": "", "route": "nljk525e", "translation": ["bzpwrkeh"], "type": "route3" },
          { "active": "1", "code": "azdq_1", "identifier": "", "image": "", "lang": "", "route": "aeu37kv3", "translation": ["a2xs5nm1"], "type": "route3" },
          { "active": "1", "code": "azdq_1", "identifier": "", "image": "", "lang": "", "route": "rgr3cp4z", "translation": ["hbisv8zx"], "type": "route3" },
          { "active": "1", "code": "azdq_1", "identifier": "", "image": "", "lang": "", "route": "nrh1wma7", "translation": ["ns2j408d"], "type": "route3" },
          { "active": "1", "code": "azdq", "identifier": "", "image": "", "lang": "", "route": "3r9x42wk", "translation": ["ffmstbn0"], "type": "route3" }
        ]
      },
      {
        "type": "entity_list",
        "lang": "",
        "translation": "qxfco1bg",
        "items": [
          { "active": "1", "code": "azdq_1", "identifier": "", "image": "", "lang": "", "route": "s1nsrlz9", "translation": ["ao3emrlo"], "type": "route3" },
          { "active": "1", "code": "azdq_1", "identifier": "", "image": "", "lang": "", "route": "d0ciftrq", "translation": ["8tm3rfdc"], "type": "route3" },
          { "active": "1", "code": "azdq_1", "identifier": "", "image": "", "lang": "", "route": "noa9vveg", "translation": ["v01gsiwo"], "type": "route3" },
          { "active": "1", "code": "azdq_1", "identifier": "", "image": "", "lang": "", "route": "bmi37vfb", "translation": ["blc3yx23"], "type": "route3" },
          { "active": "1", "code": "azdq_1", "identifier": "", "image": "", "lang": "", "route": "sc320ghf", "translation": ["zh7c0xos"], "type": "route3" },
          { "active": "1", "code": "azdq_1", "identifier": "", "image": "", "lang": "", "route": "k5mzkunj", "translation": ["iafpkazd"], "type": "route3" },
          { "active": "1", "code": "azdq_1", "identifier": "", "image": "", "lang": "", "route": "r8vi5dpk", "translation": ["wyxchkgo"], "type": "route3" },
          { "active": "1", "code": "azdq_1", "identifier": "", "image": "", "lang": "", "route": "14yxwjxa", "translation": ["i1go1hpp"], "type": "route3" },
          { "active": "1", "code": "azdq_1", "identifier": "", "image": "", "lang": "", "route": "b8bx92lk", "translation": ["zemh3n34"], "type": "route3" },
          { "active": "1", "code": "azdq_1", "identifier": "", "image": "", "lang": "", "route": "szwrht3s", "translation": ["uv9iuu37"], "type": "route3" },
          { "active": "1", "code": "azdq_1", "identifier": "", "image": "", "lang": "", "route": "tgmtw3d5", "translation": ["ox0l2b9b"], "type": "route3" },
          { "active": "1", "code": "azdq_1", "identifier": "", "image": "", "lang": "", "route": "xa7hqyir", "translation": ["hruripe1"], "type": "route3" },
          { "active": "1", "code": "azdq_1", "identifier": "", "image": "", "lang": "", "route": "yke0pw7s", "translation": ["ohfe1zrb"], "type": "route3" },
          { "active": "1", "code": "azdq_1", "identifier": "", "image": "", "lang": "", "route": "q8mob551", "translation": ["wmin7o5a"], "type": "route3" },
          { "active": "1", "code": "azdq_1", "identifier": "", "image": "", "lang": "", "route": "yxqprii5", "translation": ["prlqou9c"], "type": "route3" },

          { "active": "1", "code": "azdq_1", "identifier": "", "image": "", "lang": "", "route": "k8jklpg0", "translation": ["hcawgp3e"], "type": "route3" },
          { "active": "1", "code": "azdq_1", "identifier": "", "image": "", "lang": "", "route": "gg5lav9d", "translation": ["w2v3vdqj"], "type": "route3" },
          { "active": "1", "code": "azdq_1", "identifier": "", "image": "", "lang": "", "route": "b2hifjpg", "translation": ["jashw8c4"], "type": "route3" },
          { "active": "1", "code": "azdq_1", "identifier": "", "image": "", "lang": "", "route": "jto1xuki", "translation": ["o5h8jrz7"], "type": "route3" },
          { "active": "1", "code": "azdq_1", "identifier": "", "image": "", "lang": "", "route": "aqhfhf8b", "translation": ["8y3r7f95"], "type": "route3" },
          { "active": "1", "code": "azdq_1", "identifier": "", "image": "", "lang": "", "route": "pv0p0gch", "translation": ["ddv2r4i3"], "type": "route3" },
          { "active": "1", "code": "azdq_1", "identifier": "", "image": "", "lang": "", "route": "x8xoodca", "translation": ["q3ibadex"], "type": "route3" },
          { "active": "1", "code": "azdq_1", "identifier": "", "image": "", "lang": "", "route": "wzo2dtne", "translation": ["a2xs5nm1"], "type": "route3" },
          { "active": "1", "code": "azdq_1", "identifier": "", "image": "", "lang": "", "route": "hrqe910k", "translation": ["hbisv8zx"], "type": "route3" },
          { "active": "1", "code": "azdq_1", "identifier": "", "image": "", "lang": "", "route": "l5fpfdzx", "translation": ["ns2j408d"], "type": "route3" },
          { "active": "1", "code": "azdq_1", "identifier": "", "image": "", "lang": "", "route": "kf4heh9h", "translation": ["0yaqyr50"], "type": "route3" }
        ]
      }
    ]
  }
]