[
  { "type": "title", "lang": "zh", "translation": "57d2wlv9", "identifier": "" },
  { "type": "topic", "lang": "", "translation": "jnfvwgrt", "identifier": "" },
  { "type": "image_gallery_title", "lang": "", "translation": "ffhq0gea", "identifier": "" },
  {
    "type": "image_gallery",
    "items": [
      { "active": "1", "code": "zhfa_1", "identifier": "", "image_group": "85xvpiuj", "lang": "", "route": "8tc5zxs0", "translation": ["twb054en"], "type": "image_group1" },
      { "active": "1", "code": "zhfa_1", "identifier": "", "image_group": "llap15hf", "lang": "", "route": "n9uohpm3", "translation": ["blc3yx23"], "type": "image_group1" },
      { "active": "1", "code": "zhfa_1", "identifier": "", "image_group": "7q41yv9i", "lang": "", "route": "v915wy8k", "translation": ["4bwdhhmz"], "type": "image_group1" }
    ]
  },
  { "type": "image_gallery_title", "lang": "", "translation": "qxfco1bg", "identifier": "" },
  {
    "type": "image_gallery",
    "items": [
      { "active": "1", "code": "shfh_1", "identifier": "", "image_group": "53vlqtrl", "lang": "", "route": "b2hifjpg", "translation": ["jashw8c4"], "type": "image_group1" }
    ]
  }
]